{
  "project_info": {
    "project_number": "760833460039",
    "project_id": "cicd-demo-370312",
    "storage_bucket": "cicd-demo-370312.appspot.com"
  },
  "client": [
    {
      "client_info": {
        "mobilesdk_app_id": "1:760833460039:android:745262bc42a882af452e62",
        "android_client_info": {
          "package_name": "com.cicddemo.app"
        }
      },
      "oauth_client": [
        {
          "client_id": "760833460039-dve8ra1q5dmrdrv1an8e614kqfsjkhf5.apps.googleusercontent.com",
          "client_type": 3
        }
      ],
      "api_key": [
        {
          "current_key": "AIzaSyCyaFp-pSzKdRb0GGn5E9lryZ0umyc817M"
        }
      ],
      "services": {
        "appinvite_service": {
          "other_platform_oauth_client": [
            {
              "client_id": "760833460039-dve8ra1q5dmrdrv1an8e614kqfsjkhf5.apps.googleusercontent.com",
              "client_type": 3
            }
          ]
        }
      }
    }
  ],
  "configuration_version": "1"
}